segdtw/__init__.py
segdtw/distance.py
segdtw/tests/__init__.py
segdtw-0.1.0.dist-info/WHEEL
segdtw-0.1.0.dist-info/METADATA
segdtw-0.1.0.dist-info/RECORD
