Metadata-Version: 2.1
Name: segdtw
Version: 0.1.0
Summary: 
Author: stegben
Author-email: stegben.benjamin@gmail.com
Requires-Python: >=3.5
Classifier: Programming Language :: Python :: 3
Classifier: Programming Language :: Python :: 3.5
Classifier: Programming Language :: Python :: 3.6
Classifier: Programming Language :: Python :: 3.7
Classifier: Programming Language :: Python :: 3.8
Requires-Dist: numpy (>=1.18.2,<2.0.0)
